localmail/__init__.py
localmail/cred.py
localmail/http.py
localmail/imap.py
localmail/inbox.py
localmail/smtp.py
localmail/templates/index.html
localmail_redux-0.2.0.dist-info/LICENSE.txt
localmail_redux-0.2.0.dist-info/WHEEL
localmail_redux-0.2.0.dist-info/METADATA
localmail_redux-0.2.0.dist-info/RECORD
