Metadata-Version: 2.1
Name: localmail-redux
Version: 0.2.0
Summary: 
License: GNU
Author: Robert Hales
Author-email: rob.hales@xelix.com
Requires-Python: >=3.6.7
Classifier: License :: Other/Proprietary License
Classifier: Programming Language :: Python :: 3
Classifier: Programming Language :: Python :: 3.10
Classifier: Programming Language :: Python :: 3.7
Classifier: Programming Language :: Python :: 3.8
Classifier: Programming Language :: Python :: 3.9
Requires-Dist: Jinja2 (>=2)
Requires-Dist: Twisted (>=22.4.0,<23.0.0)
Requires-Dist: crochet (>=2.0.0,<3.0.0)
Requires-Dist: zope.interface (>=5.4.0,<6.0.0)
